doclify/__init__.py
doclify/components/__init__.py
doclify/components/init.py
doclify/components/refresh.py
doclify/components/run.py
doclify/components/update.py
doclify/config/__init__.py
doclify/config/constants.py
doclify/pipelines/__init__.py
doclify/pipelines/supervisor.py
doclify/resources/Python.gitignore
doclify/resources/__init__.py
doclify/schema/schema.py
doclify/utils/__init__.py
doclify/utils/extract.py
doclify/utils/file_utils.py
doclify/utils/llm.py
doclify/utils/logger.py
doclify/utils/readme.py
doclify/utils/scanner.py
doclify/utils/utils.py
doclify-0.2.1.dist-info/licenses/LICENSE
doclify-0.2.1.dist-info/METADATA
doclify-0.2.1.dist-info/WHEEL
doclify-0.2.1.dist-info/entry_points.txt
doclify-0.2.1.dist-info/top_level.txt
doclify-0.2.1.dist-info/RECORD
