Metadata-Version: 2.4
Name: doclify
Version: 0.2.1
Summary: AI-powered documentation generator for Python projects
Author-email: Hema Kalyan <mhemakalyan@gmail.com>
License: GNU AFFERO GENERAL PUBLIC LICENSE
Project-URL: Repository, https://github.com/KalyanM45/Doclify
Project-URL: Issues, https://github.com/KalyanM45/Doclify/issues
Requires-Python: >=3.8
License-File: LICENSE
Requires-Dist: click
Requires-Dist: google-genai
Requires-Dist: pathspec>=1.0.3
Requires-Dist: pyyaml
Requires-Dist: rich
Requires-Dist: twine>=6.2.0
Dynamic: license-file
